<annotation>
	<folder>images</folder>
	<filename>00191.jpg</filename>
	<path>C:\Users\LENOVO\darkflow\training\images\00191.jpg</path>
	<source>
		<database>Unknown</database>
	</source>
	<size>
		<width>640</width>
		<height>570</height>
		<depth>3</depth>
	</size>
	<segmented>0</segmented>
	<object>
		<name>licenseplate</name>
		<pose>Unspecified</pose>
		<truncated>0</truncated>
		<difficult>0</difficult>
		<bndbox>
			<xmin>205</xmin>
			<ymin>359</ymin>
			<xmax>476</xmax>
			<ymax>430</ymax>
		</bndbox>
	</object>
</annotation>
